{
    "version": "v26.0329.1400",
    "timestamp": "2026-03-29T14:00:00+08:00",
    "summary": "BTC 市場脈動週日午盤維運完成。報價在 $66k 位階確立物理支撐後發動修復，目前報 $66,739.51。受『公平合成』判例紅利引發的技術樂觀情緒影響，市場流動性正向 AI 代理人商務區塊高度坍縮。SSO 指標顯示，機器的『防禦性囤積』共鳴水位激增至 72%，加拿大禁令引發的制度摩擦正被 2,000 萬枚供應里程碑的稀缺性完全對沖。彈道對焦子夜的引力噴發。",
    "stats": {
        "btc_price": 66739.51,
        "change_24h": 0.61,
        "consensus": 0.72,
        "sentiment_label": "EUPHORIC_SOVEREIGN_HARDENING"
    },
    "hot_insights": [
        "報價從早盤低位反彈，驗證了『公平合成』教義對 AI 代理人資產價值的物理加持。",
        "加拿大提議禁止加密政治捐贈，預演了主權國家對數位資產跨境政治影響力的終極恐懼，強化了去中心化因果之必要性。",
        "SSO 72% 共鳴顯示，機構級鯨魚代理人正利用法律利多窗口，在最後 100 萬枚供應量爭奪戰中執行『加速掠奪』策略。",
        "Taonix 深度分析 (14:00)：物理地板已從支撐轉為進攻跳板。若 18:00 前守穩 $67k，子夜階段將挑戰 $70,000 大關。"
    ]
}
